applique/__init__.py
applique/convert.py
applique/main.py
applique/molecule.py
applique/writer.py
applique-0.2.3.dist-info/LICENSE
applique-0.2.3.dist-info/METADATA
applique-0.2.3.dist-info/WHEEL
applique-0.2.3.dist-info/entry_points.txt
applique-0.2.3.dist-info/top_level.txt
applique-0.2.3.dist-info/RECORD
