Metadata-Version: 2.1
Name: applique
Version: 0.2.3
Summary: Chemical drawing with Python
Author-email: "Julian M. Kleber" <julian.m.kleber@gmail.com>
Project-URL: Homepage, https://www.codeberg.org/cap_jmk/applique.git
Project-URL: Bug Tracker, https://www.codeberg.org/cap_jmk/applique.git/issues
Classifier: Programming Language :: Python :: 3
Classifier: License :: OSI Approved :: GNU General Public License v3 (GPLv3)
Classifier: Operating System :: OS Independent
Requires-Python: >=3.8
License-File: LICENSE
Requires-Dist: amarium
Requires-Dist: rdkit
Requires-Dist: mond
Requires-Dist: molmass
